Metadata-Version: 2.1
Name: inputmanager
Version: 1.0.2
Summary: a few function to get clean inputs from a user
Home-page: https://github.com/tristanmsct/Terminal
Author: Tristan Muscat
Author-email: traistan.muscat@gmail.com
License: MIT
Platform: unix
Platform: linux
Platform: osx
Platform: cygwin
Platform: win32
Classifier: Programming Language :: Python :: 3
Classifier: Programming Language :: Python :: 3 :: Only
Classifier: Programming Language :: Python :: 3.6
Classifier: Programming Language :: Python :: 3.7
Classifier: Programming Language :: Python :: 3.8
Classifier: Programming Language :: Python :: 3.9
Requires-Python: >=3.6
Provides-Extra: testing
